freem_protocols/__init__.py
freem_protocols/py.typed
freem_protocols/freem_box/__init__.py
freem_protocols/freem_box/audio_pb2.py
freem_protocols/freem_box/audio_pb2.pyi
freem_protocols/freem_box/audio_pb2_grpc.py
freem_protocols/freem_box/spotify_pb2.py
freem_protocols/freem_box/spotify_pb2.pyi
freem_protocols/freem_box/spotify_pb2_grpc.py
freem_protocols/furgame_league_protogen/__init__.py
freem_protocols/furgame_league_protogen/control_pb2.py
freem_protocols/furgame_league_protogen/control_pb2.pyi
freem_protocols/furgame_league_protogen/control_pb2_grpc.py
freem_protocols-1.7.0.dist-info/METADATA
freem_protocols-1.7.0.dist-info/WHEEL
freem_protocols-1.7.0.dist-info/top_level.txt
freem_protocols-1.7.0.dist-info/RECORD
