Metadata-Version: 2.1
Name: freem-protocols
Version: 1.7.0
Summary: Autogenerated gRPC code
Home-page: https://gitlab.com/torsten-projects/grpc-protocols
Author: Jakub Rohla
Author-email: freemanovec@protonmail.com
Classifier: Programming Language :: Python :: 3
Classifier: License :: OSI Approved :: MIT License
Classifier: Operating System :: OS Independent
Requires-Python: >=3.11
Requires-Dist: grpcio (==1.51.3)
Requires-Dist: protobuf (==4.22.0)
